{
    "id": "https://github.com/letresearchunit/xapi/bookroll/profile",
    "@context": "https://w3id.org/xapi/profiles/context",
    "type": "Profile",
    "conformsTo": "https://w3id.org/xapi/profiles#1.0",
    "prefLabel": {
        "en": "xAPI BookRoll Profile",
        "fr": "Profil xAPI pour BookRoll",
        "jp": ""
    },
    "definition" : {
        "en": "",
        "fr": "",
        "jp": ""
    },
    "seeAlso": "https://github.com/letresearchunit/xapi/blob/master/bookroll/bookroll_Extension_for_xAPI.md",
    "versions": [
        {
            "id": "https://github.com/letresearchunit/xapi/bookroll/profile/v1.0",
            "generatedAtTime": "2020-05-20T12:00:00Z"
        }
    ],
    "author": {
        "type": "Organization",
        "name": "LET Research unit, Kyoto University"
    },
    "concepts": [
        {"id": "https://github.com/letresearchunit/xapi/bookroll/extensions/log_id,
        "type": "ActivityExtension",
        "inScheme": "https://github.com/letresearchunit/xapi/bookroll/profile",
        "definition": {
            "en":"",
        "jp":"ログが出力されるたびに、順番に付与されるログの識別番号"},
        "prefLabel": {
            "en":"log_id",
        "jp":"ログID"},
        "inlineSchema": "{ \"type\": \"string\" }"
        },
        {"id": "https://github.com/letresearchunit/xapi/bookroll/extensions/contents_id,
        "type": "ActivityExtension",
        "inScheme": "https://github.com/letresearchunit/xapi/bookroll/profile",
        "definition": {
            "en":"",
        "jp":"アップロードしたPDF教材に、自動的に付与される識別ID。PDFを更新した場合でもIDは引き継がれる（新たにID付与されない）"},
        "prefLabel": {
            "en":"contents_id",
        "jp":"コンテンツID"},
        "inlineSchema": "{ \"type\": \"string\" }"
        },
        {"id": "https://github.com/letresearchunit/xapi/bookroll/extensions/contents_name,
        "type": "ActivityExtension",
        "inScheme": "https://github.com/letresearchunit/xapi/bookroll/profile",
        "definition": {
            "en":"",
        "jp":"PDFアップロード時につけた教材名"},
        "prefLabel": {
            "en":"contents_name",
        "jp":"コンテンツ名"},
        "inlineSchema": "{ \"type\": \"string\" }"
        },
        {"id": "https://github.com/letresearchunit/xapi/bookroll/extensions/description,
        "type": "ActivityExtension",
        "inScheme": "https://github.com/letresearchunit/xapi/bookroll/profile",
        "definition": {
            "en":"",
        "jp":"ジャンプ先のページ番号の‐1の値 例：P3からP6にジャンプする場合は、5 / 手書きメモの1ストロークを表す:[pen color][Multiple{UNIX time:x−coordinate:y−coordinate,...}: rgb(0,0,0),1545 888614255:56.0 0522193211488 :20.3188491774 757,154588861 4366:59.451697 12793733:20.92 8109910874298...]"},
        "prefLabel": {
            "en":"description",
        "jp":"ディスクリプション"},
        "inlineSchema": "{ \"type\": \"string\" }"
        },
        {"id": "https://github.com/letresearchunit/xapi/bookroll/extensions/device_code,
        "type": "ActivityExtension",
        "inScheme": "https://github.com/letresearchunit/xapi/bookroll/profile",
        "definition": {
            "en":"",
        "jp":"BookRollにアクセスしたときのデバイス PC パソコン端末, TABLET  タブレット端末, MOBILE モバイル端末"},
        "prefLabel": {
            "en":"device_code",
        "jp":"デバイス名"},
        "inlineSchema": "{ \"type\": \"string\" }"
        },
        {"id": "https://github.com/letresearchunit/xapi/bookroll/extensions/marker_color,
        "type": "ActivityExtension",
        "inScheme": "https://github.com/letresearchunit/xapi/bookroll/profile",
        "definition": {
            "en":"",
        "jp":"教材に引かれたマーカーの色 rgb(255,255,0)  黄色マーカー, rgb(255,0,0)    赤色マーカー"},
        "prefLabel": {
            "en":"marker_color",
        "jp":"マーカーの色"},
        "inlineSchema": "{ \"type\": \"string\" }"
        },
        {"id": "https://github.com/letresearchunit/xapi/bookroll/extensions/marker_position,
        "type": "ActivityExtension",
        "inScheme": "https://github.com/letresearchunit/xapi/bookroll/profile",
        "definition": {
            "en":"",
        "jp":"マーカーが引かれた場所について、【始点x,始点y,幅,高さ,キャンバス座標幅,キャンバス座標高さ】の6点を表示"},
        "prefLabel": {
            "en":"marker_position",
        "jp":"マーカー個所"},
        "inlineSchema": "{ \"type\": \"string\" }"
        },
        {"id": "https://github.com/letresearchunit/xapi/bookroll/extensions/marker_text,
        "type": "ActivityExtension",
        "inScheme": "https://github.com/letresearchunit/xapi/bookroll/profile",
        "definition": {
            "en":"",
        "jp":"マーカーを引いた範囲内で抽出された文章"},
        "prefLabel": {
            "en":"marker_text",
        "jp":"マーカー箇所のテキスト？"},
        "inlineSchema": "{ \"type\": \"string\" }"
        },
        {"id": "https://github.com/letresearchunit/xapi/bookroll/extensions/memo_text,
        "type": "ActivityExtension",
        "inScheme": "https://github.com/letresearchunit/xapi/bookroll/profile",
        "definition": {
            "en":"",
        "jp":"入力されたメモの文面"},
        "prefLabel": {
            "en":"memo_text",
        "jp":"メモ"},
        "inlineSchema": "{ \"type\": \"string\" }"
        },
        {"id": "https://github.com/letresearchunit/xapi/bookroll/extensions/operation_date,
        "type": "ActivityExtension",
        "inScheme": "https://github.com/letresearchunit/xapi/bookroll/profile",
        "definition": {
            "en":"",
        "jp":"各操作を行った日時（厳密にはサーバ側受信時刻で記録）"},
        "prefLabel": {
            "en":"operation_date",
        "jp":"操作日時"},
        "inlineSchema": "{ \"type\": \"string\" }"
        },
        {"id": "https://github.com/letresearchunit/xapi/bookroll/extensions/operation_name,
        "type": "ActivityExtension",
        "inScheme": "https://github.com/letresearchunit/xapi/bookroll/profile",
        "definition": {
            "en":"",
        "jp":"各操作, PAGE_JUMP    （スライダー操作など）ページ番号の指定, NEXT   次のページ指定, PREV   前のページ指定, MEMO_JUMP  メモリストの指定によるページ切替, SEARCH_JUMP   検索結果の指定によるページ切替, BOOKMARK_JUMP  しおり指定によるページ切替, LINK_CLICK   ページ内のURLリンクのクリック, ADD MARKER    マーカーの追加, DELETE MARKER  マーカーの削除, ADD BOOKMARK   しおりの追加, DELETE BOOKMARK しおりの削除, ADD MEMO    メモの追加, DELETE_MEMO  メモの削除, CHANGE MEMO  メモの編集, ADD_HW_MEMO 手書きストローク追加, UNDO_HW_MEMO 手書きUNDO処理, CLEAR_HW_MEMO 手書きCLEAR処理, SEARCH   本文内検索実行, CLOSE  教材を閉じる, OPEN    教材を開く, REGIST CONTENTS  教材の登録"},
        "prefLabel": {
            "en":"operation_name",
            "jp":"操作名},"
            "inlineSchema": "{ \"type\": \"string\" }"
            },
            {"id": "https://github.com/letresearchunit/xapi/bookroll/extensions/page_no,
            "type": "ActivityExtension",
            "inScheme": "https://github.com/letresearchunit/xapi/bookroll/profile",
            "definition": {
                "en":"",
            "jp":"操作を行った際のページ番号（１オリジン）ページジャンプの場合は移動元のページ番号 例：P3からP6にジャンプする場合は、3"},
            "prefLabel": {
                "en":"page_no",
            "jp":"ページ番号"},
            "inlineSchema": "{ \"type\": \"string\" }"
            },
            {"id": "https://github.com/letresearchunit/xapi/bookroll/extensions/process_code,
            "type": "ActivityExtension",
            "inScheme": "https://github.com/letresearchunit/xapi/bookroll/profile",
            "definition": {
                "en":"",
            "jp":"operation_nameに対応するコード , 015  PAGE_JUMPのコード, 003  NEXTのコード, 002   PREVのコード, 015   MEMO_JUMPのコード, 015  SEARCH_JUMPのコード, 015    BOOKMARK_JUMPのコード, 030  LINK_CLICKのコード, 016 ADD MARKERのコード, 018 DELETE MARKERのコード, 004  ADD BOOKMARKのコード, 006   DELETE BOOKMARKのコード, 019    ADD MEMOのコード, 022   DELETE_MEMOのコード, 020    CHANGE MEMOのコード, 007    SEARCHのコード, 024 CLOSEのコード, 023  OPENのコード"},
            "prefLabel": {
                "en":"process_code",
            "jp":"プロセスコード"},
            "inlineSchema": "{ \"type\": \"string\" }"
            },
            {"id": "https://github.com/letresearchunit/xapi/bookroll/extensions/user_id,
            "type": "ActivityExtension",
            "inScheme": "https://github.com/letresearchunit/xapi/bookroll/profile",
            "definition": {
                "en":"",
            "jp":"ログイン時に入力するユーザID ※BookRoll（LDAP含む）以外の権限認証の際は、権限を認証しているサーバのURLが@以下に付加される（user@moodle.hoge.comのように、別途タブにサンプルあり）"},
            "prefLabel": {
                "en":"user_id",
            "jp":"ユーザID"},
            "inlineSchema": "{ \"type\": \"string\" }"
            },
            {"id": "https://github.com/letresearchunit/xapi/bookroll/extensions/version,
            "type": "ActivityExtension",
            "inScheme": "https://github.com/letresearchunit/xapi/bookroll/profile",
            "definition": {
                "en":"",
            "jp":"PDF教材を更新する毎に付与されるバージョン番号（１オリジン）"},
            "prefLabel": {
                "en":"version",
            "jp":"バージョン"},
            "inlineSchema": "{ \"type\": \"string\" }"
            }
        ]
}
